[
  {
    "op": "replace",
    "path": "/data/VAULTHOST",
    "value": "https://vault-spi-vault.apps.ci-op-7b8t1wxg-32785.rhtap-perfscale.devcluster.openshift.com"
  },
  {
    "op": "add",
    "path": "/data/INSTANCEID",
    "value": "remotesecret-dev"
  },
  {
    "op": "add",
    "path": "/data/ENABLEREMOTESECRETS",
    "value": "true"
  },
  {
    "op": "add",
    "path": "/data/VAULTINSECURETLS",
    "value": "true"
  },
  {
    "op": "add",
    "path": "/data/ZAPLOGLEVEL",
    "value": "debug"
  }
]
